agentbill/__init__.py
agentbill/client.py
agentbill/tracer.py
agentbill/types.py
agentbill-1.0.0.dist-info/licenses/LICENSE
agentbill-1.0.0.dist-info/METADATA
agentbill-1.0.0.dist-info/WHEEL
agentbill-1.0.0.dist-info/top_level.txt
agentbill-1.0.0.dist-info/RECORD
