Metadata-Version: 2.4
Name: agentbill
Version: 1.0.0
Summary: OpenTelemetry-based SDK for tracking AI agent usage and billing
Home-page: https://github.com/Agent-Bill/python
Author: AgentBill
Author-email: support@agentbill.com
Keywords: opentelemetry otel ai agent billing usage-tracking openai anthropic llm observability
Classifier: Development Status :: 4 - Beta
Classifier: Intended Audience :: Developers
Classifier: Topic :: Software Development :: Libraries :: Python Modules
Classifier: License :: OSI Approved :: MIT License
Classifier: Programming Language :: Python :: 3
Classifier: Programming Language :: Python :: 3.8
Classifier: Programming Language :: Python :: 3.9
Classifier: Programming Language :: Python :: 3.10
Classifier: Programming Language :: Python :: 3.11
Requires-Python: >=3.8
License-File: LICENSE
Requires-Dist: httpx>=0.24.0
Provides-Extra: openai
Requires-Dist: openai>=1.0.0; extra == "openai"
Provides-Extra: anthropic
Requires-Dist: anthropic>=0.9.0; extra == "anthropic"
Dynamic: author
Dynamic: author-email
Dynamic: classifier
Dynamic: description
Dynamic: description-content-type
Dynamic: home-page
Dynamic: keywords
Dynamic: license-file
Dynamic: provides-extra
Dynamic: requires-dist
Dynamic: requires-python
Dynamic: summary
